README.md
setup.py
scapyshark/__init__.py
scapyshark/scapyshark.py
scapyshark/scrolling.py
scapyshark/version.py
scapyshark.egg-info/PKG-INFO
scapyshark.egg-info/SOURCES.txt
scapyshark.egg-info/dependency_links.txt
scapyshark.egg-info/entry_points.txt
scapyshark.egg-info/requires.txt
scapyshark.egg-info/top_level.txt
scapyshark/menu/__init__.py
scapyshark/menu/files.py
scapyshark/menu/main_menu.py
scapyshark/menu/research.py
scapyshark/menu/stats.py
scapyshark/packetinfo/__init__.py
scapyshark/sniffer/__init__.py
scapyshark/sniffer/sniffer.py
scapyshark/sniffer/handlers/DNS.py
scapyshark/sniffer/handlers/PcapList.py
scapyshark/sniffer/handlers/PcapSummary.py
scapyshark/sniffer/handlers/PcapWriteStream.py
scapyshark/sniffer/handlers/__init__.py